<?xml version="1.0" encoding="utf-8"?>
<!-- Created by ModBuddy on 8/11/2018 7:31:41 PM -->
<GameData>

	<Language_en_US>
		<Delete Tag="TXT_KEY_POLICY_COLLECTIVE_RULE_HELP" />
		<Row Tag="TXT_KEY_POLICY_COLLECTIVE_RULE_HELP">
			<Text>[COLOR_POSITIVE_TEXT]Collective Rule[ENDCOLOR][NEWLINE]Speeds the training of [COLOR_POSITIVE_TEXT]Settlers[ENDCOLOR] by 50% in the [ICON_CAPITAL] Capital and a free Settler appears near the [ICON_CAPITAL] Capital.</Text>
		</Row>
	</Language_en_US>
	<Language_DE_DE>
		<Delete Tag="TXT_KEY_POLICY_COLLECTIVE_RULE_HELP" />
		<Row Tag="TXT_KEY_POLICY_COLLECTIVE_RULE_HELP">
			<Text>[COLOR_WARNING_TEXT](DE_DE text) [ENDCOLOR][COLOR_POSITIVE_TEXT]Collective Rule[ENDCOLOR][NEWLINE]Speeds the training of [COLOR_POSITIVE_TEXT]Settlers[ENDCOLOR] by 50% in the [ICON_CAPITAL] Capital and a free Settler appears near the [ICON_CAPITAL] Capital.</Text>
		</Row>
	</Language_DE_DE>
	<Language_PL_PL>
		<Delete Tag="TXT_KEY_POLICY_COLLECTIVE_RULE_HELP" />
		<Row Tag="TXT_KEY_POLICY_COLLECTIVE_RULE_HELP">
			<Text>[COLOR_WARNING_TEXT](PL_PL text) [ENDCOLOR][COLOR_POSITIVE_TEXT]Collective Rule[ENDCOLOR][NEWLINE]Speeds the training of [COLOR_POSITIVE_TEXT]Settlers[ENDCOLOR] by 50% in the [ICON_CAPITAL] Capital and a free Settler appears near the [ICON_CAPITAL] Capital.</Text>
		</Row>
	</Language_PL_PL>
	<Language_RU_RU>
		<Delete Tag="TXT_KEY_POLICY_COLLECTIVE_RULE_HELP" />
		<Row Tag="TXT_KEY_POLICY_COLLECTIVE_RULE_HELP">
			<Text>[COLOR_WARNING_TEXT](RU_RU text) [ENDCOLOR][COLOR_POSITIVE_TEXT]Collective Rule[ENDCOLOR][NEWLINE]Speeds the training of [COLOR_POSITIVE_TEXT]Settlers[ENDCOLOR] by 50% in the [ICON_CAPITAL] Capital and a free Settler appears near the [ICON_CAPITAL] Capital.</Text>
		</Row>
	</Language_RU_RU>
  
</GameData>